listreqs/__init__.py
listreqs/__main__.py
listreqs/listreqs_sh.py
Listreqs-0.0.5.dist-info/LICENSE
Listreqs-0.0.5.dist-info/METADATA
Listreqs-0.0.5.dist-info/WHEEL
Listreqs-0.0.5.dist-info/entry_points.txt
Listreqs-0.0.5.dist-info/top_level.txt
Listreqs-0.0.5.dist-info/RECORD
