Metadata-Version: 2.1
Name: Listreqs
Version: 0.0.5
Summary: Listreqs is a simple requirements.txt generator. It's an alternative to pipreqs.
Home-page: https://github.com/soumya997/Listreqs
Author: Soumyadip Sarkar
Author-email: soumya997.sarkar@gmail.com
License: MIT
Platform: UNKNOWN
